uglier/__init__.py
uglier/cli.py
uglier/colored_logger.py
uglier/patcher.py
uglier/tools/__init__.py
uglier/tools/generate_characters.py
uglier-0.0.5.dist-info/METADATA
uglier-0.0.5.dist-info/WHEEL
uglier-0.0.5.dist-info/entry_points.txt
uglier-0.0.5.dist-info/top_level.txt
uglier-0.0.5.dist-info/RECORD
