Metadata-Version: 2.1
Name: uglier
Version: 0.0.5
Summary: An (alternative) tool to turn your clean python code into a hideous mess.
Home-page: UNKNOWN
Author: Jonathan Li
License: mit
Project-URL: GitHub, https://github.com/MonliH/uglier
Platform: UNKNOWN
Classifier: Programming Language :: Python :: 3
Classifier: License :: OSI Approved :: MIT License
Classifier: Operating System :: OS Independent
Requires-Python: >=3.9
